drf_msal_jwt/__init__.py
drf_msal_jwt/admin.py
drf_msal_jwt/apps.py
drf_msal_jwt/exceptions.py
drf_msal_jwt/models.py
drf_msal_jwt/serializer.py
drf_msal_jwt/settings.py
drf_msal_jwt/urls.py
drf_msal_jwt/utils.py
drf_msal_jwt/views.py
drf_msal_jwt/static/css/drf_msal_jwt.css
drf_msal_jwt/static/js/drf_msal_jwt.js
drf_msal_jwt/templates/drf_msal_jwt/base.html
drf_msal_jwt/test_utils/__init__.py
drf_msal_jwt/test_utils/test_app/__init__.py
drf_msal_jwt/test_utils/test_app/admin.py
drf_msal_jwt/test_utils/test_app/apps.py
drf_msal_jwt/test_utils/test_app/models.py
drf_msal_jwt/test_utils/test_app/migrations/__init__.py
drf_msal_jwt-0.4.0.dist-info/AUTHORS.rst
drf_msal_jwt-0.4.0.dist-info/LICENSE
drf_msal_jwt-0.4.0.dist-info/METADATA
drf_msal_jwt-0.4.0.dist-info/WHEEL
drf_msal_jwt-0.4.0.dist-info/top_level.txt
drf_msal_jwt-0.4.0.dist-info/RECORD
