Metadata-Version: 2.1
Name: drf-msal-jwt
Version: 0.4.0
Summary: Connect Django Rest Framework with MSAL and JWT
Home-page: https://github.com/narongdejsrn/drf-msal-jwt
Author: Narongdej Sarnsuwan
Author-email: narongdej@sarnsuwan.com
License: MIT
Keywords: drf-msal-jwt
Platform: UNKNOWN
Classifier: Development Status :: 3 - Alpha
Classifier: Framework :: Django :: 2.1
Classifier: Intended Audience :: Developers
Classifier: License :: OSI Approved :: BSD License
Classifier: Natural Language :: English
Classifier: Programming Language :: Python :: 3
Requires-Dist: msal (>=1.1.0)
Requires-Dist: requests (>=2.23.0)
